Workbook

Sheet Summary
B2: Bank Reconciliation - LAKESHORE UNIVERSITY , LLC
B3: WFB Account number 4121510457
B4: 45901
B5: Bank Information
F7: Balance per bank at the month end | H7: 0
B9: Outstanding Bank Deposits:
B12: Outstanding Bank Disbursement:
B14: 09/30/2025 | C14: AP | E14: STAGECOACH SWEEP DEBIT | G14: -455713.94
F16: Outstanding Items Total | H16: =SUM(G11:G14) -> -455713.94
F18: Adjusted bank balance | H18: =+H7-H16 -> 455713.94
B20: General Ledger Information - 11100014 LAKESHORE UNIVERSITY LLC - WFB
F22: Balance per TB at the month end | H22: =GL!I318 -> 222728.21
B24: Un-reconcile Outstanding Deposits:
B27: Un-reconcile Deposits: | D27: Sep' 25
B29: 45929 | C29: AR | D29: J-320131 | E29: Deposit of 09-2025 transfer funds for SD activity | G29: 2187.78
B30: 45929 | C30: AR | D30: J-320135 | E30: PayLease : Cash Deposit 09/29/2025 | G30: 899.73
B31: 45930 | C31: AR | D31: J-320325 | E31: CKS 09/30/2025 Batch 0795459c-c2d8-4c95-84e6-5ba56062a645 | G31: 1735.36
B32: 45930 | C32: AR | D32: J-320325 | E32: CKS 09/30/2025 Batch 58ceb15e-b2cf-463e-8b75-06a3184abba6 | G32: 3495
B33: 45930 | C33: AR | D33: J-320325 | E33: CKS 09/30/2025 Batch 63686773-08b8-442d-ae6d-a114e92eccb1 | G33: 977
B34: 45930 | C34: AR | D34: J-320325 | E34: PayLease : Cash Deposit 09/30/2025 | G34: 914.98
B35: 45930 | C35: AR | D35: J-320325 | E35: RP : CC Deposit 09/30/2025 | G35: 918.72
B36: 45930 | C36: AR | D36: J-325125 | E36: 9.25 PB Free Lot rent-Alafaya Palms OMAR QUINONEZ #173 | G36: 270
F38: Total | G38: =SUM(G27:G37) -> 11398.57
B40: Un-reconciled Outstanding Disbursement:
B43: Un-reconciled Disbursement: | D43: Sep' 25
B45: 45923 | C45: AP | D45: 30779 | E45: Yes Energy Management, Inc. (v0002908) | G45: -63
B46: 45926 | C46: AP | D46: 30780 | E46: Atlas Law (v0000101) | G46: -8358.5
B47: 45929 | C47: AP | D47: 30781 | E47: Charter Communications (v0006510) | G47: -123.95
B48: 45930 | C48: AP | D48: 30783 | E48: Hunter Warfield (v0007270) | G48: -445.75
B49: 45930 | C49: AP | D49: 1446 | E49: Pennoni (v0007120) | G49: -1027.5
B50: 45930 | C50: AP | D50: 1447 | E50: Lakeshore Management Inc (v0000666) | G50: -29.82
B51: 45930 | C51: AP | D51: J-320322 | E51: Lakeshore University LLC mtg pymt | G51: -193875.17
B52: 45930 | C52: AP | D52: J-323192 | E52: Park Mgmt Fees Sept 2025 :Reversed by J-323339 | G52: -22690.01
B53: 45930 | C53: AP | D53: J-325227 | E53: MA September Cash Park to Home :Reversed by J-325304 | G53: -17770.6
F55: Total | G55: =SUM(G45:G54) -> -244384.3
F57: Sub-Total | G57: =SUM(G55+G38) -> -232985.73
F59: Adjusted book balance | H59: =+H22-G57 -> 455713.94
F61: Variance (s/b zero) | H61: =+H18-H59 -> 0

Sheet Summary old
B2: Bank Reconciliation - LAKESHORE UNIVERSITY , LLC
B3: WFB Account number 4121510457
B4: 45261
B5: Bank Information
F7: Balance per bank at the month end | H7: 0
B9: Outstanding Bank Deposits:
B11: 07/31/2023 | C11: AR | E11: ONLINE TRANSFER WTR7 5 REF #BB0K9HKR4L | G11: 240 | I11: email Pejman 1/31/24 | J11: =G11+G12 -> 720
B12: 08/31/2023 | C12: AR | E12: ONLINE TRANSFER LSM TO ALAFAYA WT 8 6 REF #BB0KL2BCD4 | G12: 480 | I12: email Pejman 1/31/24
B14: Outstanding Bank Disbursement:
B16: 12/29/2023 | C16: AP | E16: STAGECOACH SWEEP DEBIT | G16: -554688.4
F18: Outstanding Items Total | H18: =SUM(G11:G16) -> -553968.4
F20: Adjusted bank balance | H20: =+H7-H18 -> 553968.4
B22: General Ledger Information - 11100014 LAKESHORE UNIVERSITY LLC - WFB
F24: Balance per TB at the month end | H24: =+GL!I318 -> 222728.21
B26: Un-reconcile Outstanding Deposits:
B28: 45126 | C28: AR | D28: J-199897 | E28: Credit Card Deposit 07/19/2023 | G28: 30 | I28: emailed Pejman 1/31/24 | J28: =SUM(G28:G37) -> 660
B29: 45127 | C29: AR | D29: J-200511 | E29: Credit Card Deposit 07/20/2023 | G29: 30 | I29: emailed Pejman 1/31/24
B30: 45133 | C30: AR | D30: J-201049 | E30: Credit Card Deposit 07/26/2023 | G30: 60 | I30: emailed Pejman 1/31/24
B31: 45140 | C31: AR | D31: J-202864 | E31: Credit Card Deposit 08/02/2023 | G31: 60 | I31: emailed Pejman 1/31/24
B32: 45147 | C32: AR | D32: J-203316 | E32: Credit Card Deposit 08/09/2023 | G32: 120 | I32: emailed Pejman 1/31/24
B33: 45155 | C33: AR | D33: J-204518 | E33: Credit Card Deposit 08/17/2023 | G33: 180 | I33: emailed Pejman 1/31/24
B34: 45162 | C34: AR | D34: J-204827 | E34: Credit Card Deposit 08/24/2023 | G34: 30 | I34: emailed Pejman 1/31/24
B35: 45182 | C35: AR | D35: J-206474 | E35: Credit Card Deposit 09/13/2023 | G35: 60 | I35: emailed Pejman 1/31/24
B36: 45224 | C36: AR | D36: J-211820 | E36: Credit Card Deposit 10/25/2023 | G36: 60 | I36: emailed Pejman 1/31/24
B37: 45230 | C37: AR | D37: J-212451 | E37: Credit Card Deposit 10/31/2023 | G37: 30 | I37: emailed Pejman 1/31/24
B38: 45288 | C38: AR | D38: J-218048 | E38: PayLease : Cash Deposit 12/28/2023 | G38: 841.51 | I38: to clear Jan 2024
B39: 45291 | C39: AR | D39: J-217534 | E39: Lot 243 Pablo Javier Cruz SD credit to ledger | G39: 675 | I39: to clear Jan 2024
B40: 45291 | C40: AR | D40: J-217534 | E40: Lot 337 Lateja Renae Littles SD credit to ledger | G40: 3590 | I40: to clear Jan 2024
... B47: 45291 | C47: AR | D47: J-219857 | E47: PayLease : Cash Deposit 12/31/2023 | G47: 801.51 | I47: to clear Jan 2024
F49: Total | G49: =SUM(G28:G47) -> 16591.3
B51: Un-reconciled Outstanding Disbursement:
B53: 45097 | C53: AP | D53: 29657 | E53: BALLOONS BY RENEE (v0000109) | G53: -25.09
B54: 45163 | C54: AP | D54: 29765 | E54: John Pierre Martinez Ramos (v0007935) | G54: -3.09
B55: 45257 | C55: AP | D55: 29904 | E55: SHEAFFER INDUSTRIES (v0000974) | G55: -27000
B56: 45271 | C56: AP | D56: 29922 | E56: Communications Consulting Group, Inc. (v0008172) | G56: -234.14
B57: 45275 | C57: AP | D57: 29929 | E57: Communications Consulting Group, Inc. (v0008172) | G57: -36.98
B58: 45278 | C58: AP | D58: 29930 | E58: AtlasLaw (v0000101) | G58: -1004.27
B59: 45279 | C59: AP | D59: 29935 | E59: SHEAFFER INDUSTRIES (v0000974) | G59: -3650
B60: 45281 | C60: AP | D60: 29936 | E60: BALLOONS BY RENEE (v0000109) | G60: -25.09
B61: 45281 | C61: AP | D61: 29939 | E61: CREATIVE MULTICARE, INC. (v0001308) | G61: -200
B62: 45281 | C62: AP | D62: 29940 | E62: MICHAEL'S LIGHTING & ELECTRIC,INC (v0003348) | G62: -497.98
B63: 45286 | C63: AP | D63: 29941 | E63: DISPOSALL, INC. (v0001311) | G63: -1324.74
B64: 45286 | C64: AP | D64: 29942 | E64: DISPOSALL, INC. (v0001311) | G64: -7200
... B78: 45289 | C78: AP | D78: 29952 | E78: Barney's Pumps, Inc. (v0007883) | G78: -12533
B79: 45291 | C79: AP | D79: J-218058 | E79: 12/2023 Mortgages | G79: -192697.81
B80: 45291 | C80: AP | D80: J-219797 | E80: Park Mgmt Fees Dec 2023 :Reversed by J-219798 | G80: -19704.66
B81: 45291 | C81: AP | D81: J-219816 | E81: December 2023 Cash Park to Home :Reversed by J-219817 | G81: -24669.9
F83: Total | G83: =SUM(G53:G82) -> -301545.44
F85: Sub-Total | G85: =SUM(G83+G49) -> -284954.14
F87: Adjusted book balance | H87: =+H24-G85 -> 507682.35
F89: Variance (s/b zero) | H89: =+H20-H87 -> 46286.05

Sheet AR Notes
B2: Bank Reconciliation - LAKESHORE UNIVERSITY , LLC
B3: WFB Account number 4121510457
B4: 44652
B5: Bank Information
F7: Balance per bank at the month end | H7: 359290.86
B9: Outstanding Bank Deposits:
B11: 04/16/2021 | C11: AR | E11: Alafaya Palms - Settlement 041621 000011037449954 Lakeshore Management I 9000631441 000011037449954 R00000091004259204180 | G11: 483.07 | I11: Researching
B12: 04/27/2022 | C12: AR | E12: DESKTOP CHECK DEPOSIT | G12: 86517
B14: Outstanding Bank Disbursement:
F17: Outstanding Items Total | H17: =SUM(G11:G15) -> 87000.07
F19: Adjusted bank balance | H19: =+H7-H17 -> 272290.79
B21: General Ledger Information - 11100014 LAKESHORE UNIVERSITY LLC - WFB
F23: Balance per TB at the month end | H23: =+GL!I318 -> 222728.21
B25: Un-reconcile Outstanding Deposits:
B27: 44302 | C27: AR | D27: J-114439 | E27: RP : ACH Deposit 04/15/2021 | G27: 1442.8 | I27: $717.80 returned on 4/21/21, how was that debit cleared?
B29: Un-reconcile Deposits: | D29: Apr '22 | G29: =+GL!G321 -> 11398.57
F31: Total | G31: =SUM(G26:G30) -> 12841.37
B33: Un-reconciled Outstanding Disbursement:
B36: Un-reconcile Disbursements: | D36: Apr '22 | G36: =+GL!G323 -> -244384.3
F38: Total | G38: =SUM(G34:G37) -> -244384.3
F40: Sub-Total | G40: =SUM(G38+G31) -> -231542.93
F42: Adjusted book balance | H42: =+H23-G40 -> 454271.14
F44: Variance (s/b zero) | H44: =+H19-H42 -> -181980.35

Sheet Bank Statement
A1: Date | B1: Amount | C1: Check Number | D1: Code | E1: Description
A2: 09/02/2025 | B2: -409963.39 | D2: -4 | E2: STAGECOACH SWEEP DEBIT
A3: 09/02/2025 | B3: -165.52 | D3: -3 | E3: 014APOC BILL PAY 090225 GH3H6K 0000Lakeshore Manage 9000820926 GH3H6K 0R00000091006273434795N
A4: 09/02/2025 | B4: -137.76 | C4: 30754 | D4: -3 | E4: CHECK
A5: 09/02/2025 | B5: 19550.05 | D5: 2 | E5: Alafaya Palms - Settlement 090225 000024843797126 Lakeshore Management I 9000631441 000024843797126 R00000091006274007618N
A6: 09/02/2025 | B6: 2061.1 | D6: 3 | E6: BNKCD SETTLE MERCH DEP 250830 286000000277756 ALAFAYA PALMS MHC 1043763809 286000000277756 R00000091003951022269N
A7: 09/02/2025 | B7: 1013.39 | D7: 2 | E7: STAGECOACH SWEEP INTEREST PAYMENT
A8: 09/02/2025 | B8: 387642.13 | D8: 4 | E8: STAGECOACH SWEEP CREDIT
A9: 09/03/2025 | B9: -480855.79 | D9: -4 | E9: STAGECOACH SWEEP DEBIT
A10: 09/03/2025 | B10: -14864.49 | C10: 30761 | D10: -2 | E10: CHECK
A11: 09/03/2025 | B11: 73440.08 | D11: 2 | E11: Alafaya Palms - Settlement 090325 000024890619870 Lakeshore Management I 9000631441 000024890619870 R00000091004450150607N
A12: 09/03/2025 | B12: 10418.33 | D12: 3 | E12: PAYLEASE.COM CREDIT XXXXX1995 Lakeshore Management, 1273639005 440691995 R00000091003638354122N
A13: 09/03/2025 | B13: 950 | D13: 2 | E13: Alafaya Palms - Settlement 090325 000024881277238 Alafaya Palms - 014 9000632861 000024881277238 R00000091004450078305N
A14: 09/03/2025 | B14: 913.48 | D14: 2 | E14: BNKCD SETTLE MERCH DEP 250903 286000000277756 ALAFAYA PALMS MHC 1043763809 286000000277756 R00000091004559890423N
A15: 09/03/2025 | B15: 35 | D15: 2 | E15: Alafaya Palms - Settlement 090325 000024882182778 Alafaya Palms - 014 9000632861 000024882182778 R00000091004450142105N
A16: 09/03/2025 | B16: 409963.39 | D16: 4 | E16: STAGECOACH SWEEP CREDIT
A17: 09/04/2025 | B17: -500843.98 | D17: -4 | E17: STAGECOACH SWEEP DEBIT
A18: 09/04/2025 | B18: -3454.72 | C18: 30755 | D18: -3 | E18: CHECK
A19: 09/04/2025 | B19: -1307.15 | C19: 30758 | D19: -3 | E19: CHECK
A20: 09/04/2025 | B20: -255 | C20: 30757 | D20: -3 | E20: CHECK
A21: 09/04/2025 | B21: -22951.41 | D21: -2 | E21: ACH ORIGINATION - Alafaya Palms - FILE EDIMN00004 COID LAK3642370 LAK3642370 FILE EDIMN00004 0S00000091003637181557N
A22: 09/04/2025 | B22: 41247.87 | D22: 2 | E22: Alafaya Palms - Settlement 090425 000024906269214 Lakeshore Management I 9000631441 000024906269214 R00000091004036673458N
A23: 09/04/2025 | B23: 3700.48 | D23: 2 | E23: BNKCD SETTLE MERCH DEP 250904 286000000277756 ALAFAYA PALMS MHC 1043763809 286000000277756 R00000091004135252078N
A24: 09/04/2025 | B24: 2737.27 | D24: 2 | E24: PAYLEASE.COM CREDIT XXXXX4821 Lakeshore Management, 1273639005 441304821 R00000091004036529803N
A25: 09/04/2025 | B25: 270 | D25: 3 | E25: Lakeshore Manage BILLPAY 090425 FXH9H3 RMR*IV*8.25 PB Free Lot rent 1**270.00*270.00*0.09000688057 FXH9H3 R00000091004036904526N
A26: 09/04/2025 | B26: 196.85 | D26: 2 | E26: DESKTOP CHECK DEPOSIT
A27: 09/04/2025 | B27: 480855.79 | D27: 4 | E27: STAGECOACH SWEEP CREDIT
A28: 09/05/2025 | B28: -350214.36 | D28: -4 | E28: STAGECOACH SWEEP DEBIT
A29: 09/05/2025 | B29: -198634.81 | D29: -3 | E29: Capital One PAYMENT 090425 Capital One, N.A. 1270882098 0R00000091004531704901N
A30: 09/05/2025 | B30: -2260.69 | D30: -2 | E30: 014APOC BILL PAY 090525 Z6TJ9K 0000Lakeshore Manage 9000820926 Z6TJ9K 0R00000091004531593136N
A31: 09/05/2025 | B31: -1416 | D31: -2 | E31: Alafaya Palms - Return 090525 000024913325246 Lakeshore Management I 9000631441 000024913325246 0R00000091004531574058N
A32: 09/05/2025 | B32: -550 | C32: 30756 | D32: -3 | E32: CHECK
A33: 09/05/2025 | B33: 39168.16 | D33: 2 | E33: Alafaya Palms - Settlement 090525 000024919864994 Lakeshore Management I 9000631441 000024919864994 R00000091004531611849N
A34: 09/05/2025 | B34: 8167.98 | D34: 2 | E34: PAYLEASE.COM CREDIT XXXXX4383 Lakeshore Management, 1273639005 441754383 R00000091004531374020N
A35: 09/05/2025 | B35: 1854.72 | D35: 2 | E35: BNKCD SETTLE MERCH DEP 250905 286000000277756 ALAFAYA PALMS MHC 1043763809 286000000277756 R00000091004539933343N
A36: 09/05/2025 | B36: 970 | D36: 2 | E36: Alafaya Palms - Settlement 090525 000024917574366 Alafaya Palms - 014 9000632861 000024917574366 R00000091004531575543N
A37: 09/05/2025 | B37: 966.94 | D37: 2 | E37: Alafaya Palms - Settlement 090525 000024917574358 Alafaya Palms - 014 9000632861 000024917574358 R00000091004531601057N
A38: 09/05/2025 | B38: 908.08 | D38: 2 | E38: Alafaya Palms - Settlement 090525 000024917574350 Alafaya Palms - 014 9000632861 000024917574350 R00000091004531610936N
A39: 09/05/2025 | B39: 500843.98 | D39: 4 | E39: STAGECOACH SWEEP CREDIT
A40: 09/08/2025 | B40: -477523.6 | D40: -4 | E40: STAGECOACH SWEEP DEBIT
A41: 09/08/2025 | B41: -443.96 | D41: -2 | E41: ACH ORIGINATION - Alafaya Palms - FILE EDIMN00004 COID LAK3642370 LAK3642370 FILE EDIMN00004 0S00000091005466866509N
A42: 09/08/2025 | B42: 113743.08 | D42: 2 | E42: Alafaya Palms - Settlement 090825 000024933786530 Lakeshore Management I 9000631441 000024933786530 R00000091005569993715N
A43: 09/08/2025 | B43: 10175.59 | D43: 2 | E43: PAYLEASE.COM CREDIT XXXXX4523 Lakeshore Management, 1273639005 442194523 R00000091005570028343N
A44: 09/08/2025 | B44: 3834.53 | D44: 2 | E44: BNKCD SETTLE MERCH DEP 250906 286000000277756 ALAFAYA PALMS MHC 1043763809 286000000277756 R00000091005675715639N
... A66: 09/11/2025 | B66: -502808.79 | D66: -4 | E66: STAGECOACH SWEEP DEBIT
A67: 09/11/2025 | B67: -9233.55 | C67: 30766 | D67: -2 | E67: CHECK
A68: 09/11/2025 | B68: -7624.43 | D68: -2 | E68: Alafaya Palms - Return 091125 000024965119226 Lakeshore Management I 9000631441 000024965119226 0R00000091006370423148N
A69: 09/11/2025 | B69: -800 | C69: 30764 | D69: -2 | E69: CHECK
A70: 09/11/2025 | B70: -425 | C70: 30765 | D70: -2 | E70: CHECK
A71: 09/11/2025 | B71: -368.81 | C71: 30767 | D71: -2 | E71: CHECK
A72: 09/11/2025 | B72: -240 | C72: 30763 | D72: -2 | E72: CHECK
A73: 09/11/2025 | B73: -2058.64 | D73: -2 | E73: ACH ORIGINATION - Alafaya Palms - FILE EDIMN00004 COID LAK3642370 LAK3642370 FILE EDIMN00004 0S00000091006276901356N
A74: 09/11/2025 | B74: 4185.33 | D74: 2 | E74: ONLINE TRANSFER LSM TO ALAFAYA INS PRCDS 9 8N9 25 REF #BB0TVPGVGJ
A75: 09/11/2025 | B75: 2266 | D75: 2 | E75: Alafaya Palms - Settlement 091125 000024967322770 Alafaya Palms - 014 9000632861 000024967322770 R00000091006370086828N
A76: 09/11/2025 | B76: 2096.09 | D76: 2 | E76: Alafaya Palms - Settlement 091125 000024968902882 Lakeshore Management I 9000631441 000024968902882 R00000091006370086860N
A77: 09/11/2025 | B77: 1948 | D77: 2 | E77: Alafaya Palms - Settlement 091125 000024967322818 Alafaya Palms - 014 9000632861 000024967322818 R00000091006370092452N
A78: 09/11/2025 | B78: 513063.8 | D78: 4 | E78: STAGECOACH SWEEP CREDIT
A79: 09/12/2025 | B79: -503553.64 | D79: -4 | E79: STAGECOACH SWEEP DEBIT
A80: 09/12/2025 | B80: -100.14 | D80: -2 | E80: 014APOC BILL PAY 091225 BBYZBK 0000Lakeshore Manage 9000820926 BBYZBK 0R00000091003952413467N
A81: 09/12/2025 | B81: -56 | C81: 30759 | D81: -3 | E81: CHECK
A82: 09/12/2025 | B82: -5 | D82: -2 | E82: LAKEMGT-014APOC Settlement 091225 000024977270186 Lakeshore Management I 9000688057 000024977270186 0R00000091003952081905N
A83: 09/12/2025 | B83: -103.74 | D83: -2 | E83: ACH ORIGINATION - Alafaya Palms - FILE EDIMN00004 COID LAK3642370 LAK3642370 FILE EDIMN00004 0S00000091004056554449N
A84: 09/12/2025 | B84: 909.73 | D84: 2 | E84: Alafaya Palms - Settlement 091225 000024974902086 Alafaya Palms - 014 9000632861 000024974902086 R00000091003951575591N
A85: 09/12/2025 | B85: 50 | D85: 2 | E85: Alafaya Palms - Settlement 091225 000024976650178 Lakeshore Management I 9000631441 000024976650178 R00000091003951994277N
A86: 09/12/2025 | B86: 50 | D86: 2 | E86: BNKCD SETTLE MERCH DEP 250912 286000000277756 ALAFAYA PALMS MHC 1043763809 286000000277756 R00000091003959323182N
A87: 09/12/2025 | B87: 502808.79 | D87: 4 | E87: STAGECOACH SWEEP CREDIT
A88: 09/15/2025 | B88: -506754.53 | D88: -4 | E88: STAGECOACH SWEEP DEBIT
A89: 09/15/2025 | B89: -471.7 | C89: 30769 | D89: -2 | E89: CHECK
A90: 09/15/2025 | B90: -26.09 | C90: 30770 | D90: -2 | E90: CHECK
A91: 09/15/2025 | B91: -565.23 | D91: -2 | E91: ACH ORIGINATION - Alafaya Palms - FILE EDIMN00004 COID LAK3642370 LAK3642370 FILE EDIMN00004 0S00000091004056554681N
A92: 09/15/2025 | B92: 2187.39 | D92: 2 | E92: Alafaya Palms - Settlement 091525 000024985521890 Lakeshore Management I 9000631441 000024985521890 R00000091004350835829N
A93: 09/15/2025 | B93: 2076.52 | D93: 2 | E93: BNKCD SETTLE MERCH DEP 250913 286000000277756 ALAFAYA PALMS MHC 1043763809 286000000277756 R00000091004557570542N
A94: 09/15/2025 | B94: 503553.64 | D94: 4 | E94: STAGECOACH SWEEP CREDIT
A95: 09/16/2025 | B95: -509669.26 | D95: -4 | E95: STAGECOACH SWEEP DEBIT
A96: 09/16/2025 | B96: -244.95 | C96: 30771 | D96: -2 | E96: CHECK
A97: 09/16/2025 | B97: -90 | C97: 30768 | D97: -2 | E97: CHECK
A98: 09/16/2025 | B98: -50 | D98: -2 | E98: Alafaya Palms - Return 091625 000024994649430 Lakeshore Management I 9000631441 000024994649430 0R00000091004037924455N
A99: 09/16/2025 | B99: 3231.99 | D99: 2 | E99: Alafaya Palms - Settlement 091625 000025001142654 Lakeshore Management I 9000631441 000025001142654 R00000091004037883386N
A100: 09/16/2025 | B100: 67.69 | D100: 2 | E100: Alafaya Palms - Settlement 091625 000024993900162 Alafaya Palms - 014 9000632861 000024993900162 R00000091004037856387N
A101: 09/16/2025 | B101: 506754.53 | D101: 4 | E101: STAGECOACH SWEEP CREDIT
A102: 09/17/2025 | B102: -500602.56 | D102: -4 | E102: STAGECOACH SWEEP DEBIT
A103: 09/17/2025 | B103: -10993.85 | C103: 30777 | D103: -2 | E103: CHECK
A104: 09/17/2025 | B104: -295.4 | D104: -2 | E104: 014APOC BILL PAY 091725 M5ZBCK 0000Lakeshore Manage 9000820926 M5ZBCK 0R00000091004438298445N
A105: 09/17/2025 | B105: -115 | C105: 30762 | D105: -2 | E105: CHECK
A106: 09/17/2025 | B106: -42.4 | D106: -2 | E106: ACH ORIGINATION - Alafaya Palms - FILE EDIMN00004 COID LAK3642370 LAK3642370 FILE EDIMN00004 0S00000091004234015750N
A107: 09/17/2025 | B107: 2079.95 | D107: 2 | E107: Alafaya Palms - Settlement 091725 000025008964302 Lakeshore Management I 9000631441 000025008964302 R00000091004438213032N
A108: 09/17/2025 | B108: 300 | D108: 2 | E108: Alafaya Palms - Settlement 091725 000025005635498 Alafaya Palms - 014 9000632861 000025005635498 R00000091004438218908N
A109: 09/17/2025 | B109: 509669.26 | D109: 4 | E109: STAGECOACH SWEEP CREDIT
A110: 09/18/2025 | B110: -495660.48 | D110: -4 | E110: STAGECOACH SWEEP DEBIT
A111: 09/18/2025 | B111: -5080.11 | D111: -2 | E111: LAKEMGT-014APOC Settlement 091825 000025016428970 Lakeshore Management I 9000688057 000025016428970 0R00000091005576824454N
A112: 09/18/2025 | B112: -24 | D112: -2 | E112: ACH ORIGINATION - Alafaya Palms - FILE EDIMN00004 COID LAK3642370 LAK3642370 FILE EDIMN00004 0S00000091005460293096N
A113: 09/18/2025 | B113: 122.03 | D113: 2 | E113: ONLINE TRANSFER LSM TO ALAFAYA INS PRCD DEP 9 17 25 SOL 8 REF #BB0TY6J6PM
A114: 09/18/2025 | B114: 40 | D114: 2 | E114: Alafaya Palms - Settlement 091825 000025016013594 Lakeshore Management I 9000631441 000025016013594 R00000091005576776679N
A115: 09/18/2025 | B115: 500602.56 | D115: 4 | E115: STAGECOACH SWEEP CREDIT
A116: 09/19/2025 | B116: -492904.01 | D116: -4 | E116: STAGECOACH SWEEP DEBIT
A117: 09/19/2025 | B117: -5680 | C117: 30773 | D117: -2 | E117: CHECK
A118: 09/19/2025 | B118: -323.25 | D118: -2 | E118: INTELLIPAY BILLING 250918 A22204984 Lakeshore - Alafaya Pa 27-3685152 A22204984 0R00000091005765501144N
A119: 09/19/2025 | B119: -9.65 | D119: -2 | E119: LAKEMGT-014APOC Settlement 091925 000025023492842 Lakeshore Management I 9000688057 000025023492842 0R00000091005774396817N
A120: 09/19/2025 | B120: 2123.05 | D120: 2 | E120: Alafaya Palms - Settlement 091925 000025023009586 Lakeshore Management I 9000631441 000025023009586 R00000091005774628125N
A121: 09/19/2025 | B121: 1133.38 | D121: 2 | E121: BNKCD SETTLE MERCH DEP 250919 286000000277756 ALAFAYA PALMS MHC 1043763809 286000000277756 R00000091005861903033N
...

Sheet GL
A1: General Ledger
A2: Property: Alafaya Palms (014ap)
A3: Detail Date Range: 09/01/25 - 09/30/25 (accrual basis)
A4: 11100014 LAKESHORE UNIVERSITY LLC - WFB (Bank Account) | I4: 146158.5
A5: Property Name | B5: Date | C5: Control | D5: Reference | E5: Description | F5: Remarks | G5: Debit | H5: Credit | I5: Balance | J5: Reconcile Date | K5: Code
A6: Alafaya Palms | B6: 45901 | C6: J-313627 | D6: Daily Deposit | E6: 09/01/2025 Daily Deposit | F6: EFT Deposit 09/01/2025 | G6: 4599.85 | I6: 150758.35 | J6: 09/03/2025 | K6: 2
A7: Alafaya Palms | B7: 45901 | C7: J-313627 | D7: Daily Deposit | E7: 09/01/2025 Daily Deposit | F7: PayLease : Cash Deposit 09/01/2025 | G7: 2772.13 | I7: 153530.48 | J7: 09/03/2025 | K7: 3
A8: Alafaya Palms | B8: 45901 | C8: J-315961 | D8: :Reversal of J-315814 | E8: :Reversal of J-315814 | F8: :Reversal of J-315814 | G8: 22750.99 | I8: 176281.47 | J8: 45900 | K8: 4
A9: Alafaya Palms | B9: 45901 | C9: J-319115 | D9: :Reversal of J-319040 | E9: :Reversal of J-319040 | F9: MA August Cash Park to Home | G9: 21748.98 | I9: 198030.45 | J9: 45900 | K9: 4
A10: Alafaya Palms | B10: 45902 | C10: K-486492 | D10: 1404 | E10: Lakeshore Management Inc (v0000666) | F10: Jun 25 Invoices | H10: -200.42 | I10: 197830.03 | J10: 09/04/2025 | K10: -2
A11: Alafaya Palms | B11: 45902 | C11: K-486671 | D11: 1405 | E11: LSM NT CHECK (v0004320) | F11: Management Fees | H11: -4550.2 | I11: 193279.83 | J11: 09/04/2025 | K11: -2
A12: Alafaya Palms | B12: 45902 | C12: K-486671 | D12: 1405 | E12: LSM NT CHECK (v0004320) | F12: Management Fees | H12: -18200.79 | I12: 175079.04 | J12: 09/04/2025 | K12: -2
A13: Alafaya Palms | B13: 45902 | C13: J-316977 | D13: Daily Deposit | E13: 09/02/2025 Daily Deposit | F13: CKS 09/02/2025 Batch 7c0264bf-524f-4077-8a4c-3890c192799c | G13: 35 | I13: 175114.04 | J13: 09/03/2025 | K13: 2
A14: Alafaya Palms | B14: 45902 | C14: J-316977 | D14: Daily Deposit | E14: 09/02/2025 Daily Deposit | F14: CKS 09/02/2025 Batch aee7890e-a433-413a-8df4-0889c69a7d71 | G14: 950 | I14: 176064.04 | J14: 09/03/2025 | K14: 2
A15: Alafaya Palms | B15: 45902 | C15: J-316977 | D15: Daily Deposit | E15: 09/02/2025 Daily Deposit | F15: PayLease : Cash Deposit 09/02/2025 | G15: 2737.27 | I15: 178801.31 | J15: 09/04/2025 | K15: 2
A16: Alafaya Palms | B16: 45902 | C16: J-316977 | D16: Daily Deposit | E16: 09/02/2025 Daily Deposit | F16: RP : ACH Deposit 08/29/2025 | G16: 19550.05 | I16: 198351.36 | J16: 09/02/2025 | K16: 2
A17: Alafaya Palms | B17: 45902 | C17: J-316977 | D17: Daily Deposit | E17: 09/02/2025 Daily Deposit | F17: RP : CC Deposit 09/02/2025 | G17: 1815.93 | I17: 200167.29 | J17: 09/08/2025 | K17: 2
A18: Alafaya Palms | B18: 45902 | C18: J-319459 | D18: Sweep Interest Payment - September'25 | E18: Sweep Interest Payment - September'25 | F18: Stagecoach Sweep Interest Payment-September'25 | G18: 1013.39 | I18: 201180.68 | J18: 09/02/2025 | K18: 2
A19: Alafaya Palms | B19: 45903 | C19: K-486810 | D19: 30761 | E19: LSE (v0000665) | F19: SEP25 Health Dental | H19: -4168.25 | I19: 197012.43 | J19: 09/03/2025 | K19: -2
A20: Alafaya Palms | B20: 45903 | C20: K-486810 | D20: 30761 | E20: LSE (v0000665) | F20: SEP25 Life STD & OTH | H20: -126.62 | I20: 196885.81 | J20: 09/03/2025 | K20: -2
A21: Alafaya Palms | B21: 45903 | C21: K-486810 | D21: 30761 | E21: LSE (v0000665) | F21: SEP25 Vision | H21: -23.4 | I21: 196862.41 | J21: 09/03/2025 | K21: -2
A22: Alafaya Palms | B22: 45903 | C22: K-486810 | D22: 30761 | E22: LSE (v0000665) | F22: DEPT 15120 ppe 08/30/25 | H22: -182.08 | I22: 196680.33 | J22: 09/03/2025 | K22: -2
A23: Alafaya Palms | B23: 45903 | C23: K-486810 | D23: 30761 | E23: LSE (v0000665) | F23: DEPT 15120 ppe 08/30/25 | H23: -3901.08 | I23: 192779.25 | J23: 09/03/2025 | K23: -2
A24: Alafaya Palms | B24: 45903 | C24: K-486810 | D24: 30761 | E24: LSE (v0000665) | F24: DEPT 15120 ppe 08/30/25 | H24: -6245.26 | I24: 186533.99 | J24: 09/03/2025 | K24: -2
A25: Alafaya Palms | B25: 45903 | C25: K-486810 | D25: 30761 | E25: LSE (v0000665) | F25: DEPT 15120 ppe 08/30/25 | H25: -738.32 | I25: 185795.67 | J25: 09/03/2025 | K25: -2
A26: Alafaya Palms | B26: 45903 | C26: K-486810 | D26: 30761 | E26: LSE (v0000665) | F26: DEPT 15120 ppe 08/30/25 | H26: -91.44 | I26: 185704.23 | J26: 09/03/2025 | K26: -2
A27: Alafaya Palms | B27: 45903 | C27: K-486810 | D27: 30761 | E27: LSE (v0000665) | F27: DEPT 15120 ppe 08/30/25 | G27: 496.8 | I27: 186201.03 | J27: 09/03/2025 | K27: -2
A28: Alafaya Palms | B28: 45903 | C28: K-486810 | D28: 30761 | E28: LSE (v0000665) | F28: DEPT 15120 ppe 08/30/25 | G28: 48.27 | I28: 186249.3 | J28: 09/03/2025 | K28: -2
A29: Alafaya Palms | B29: 45903 | C29: K-486810 | D29: 30761 | E29: LSE (v0000665) | F29: DEPT 15120 ppe 08/30/25 | G29: 80.45 | I29: 186329.75 | J29: 09/03/2025 | K29: -2
A30: Alafaya Palms | B30: 45903 | C30: K-486810 | D30: 30761 | E30: LSE (v0000665) | F30: DEPT 15120 ppe 08/30/25 | G30: 14.96 | I30: 186344.71 | J30: 09/03/2025 | K30: -2
A31: Alafaya Palms | B31: 45903 | C31: K-486810 | D31: 30761 | E31: LSE (v0000665) | F31: DEPT 35200 ppe 08/30/25 | H31: -26.5 | I31: 186318.21 | J31: 09/03/2025 | K31: -2
A32: Alafaya Palms | B32: 45903 | C32: K-486810 | D32: 30761 | E32: LSE (v0000665) | F32: DEPT 35200 ppe 08/30/25 | H32: -2.02 | I32: 186316.19 | J32: 09/03/2025 | K32: -2
A33: Alafaya Palms | B33: 45903 | C33: J-317122 | E33: PDM & Hunter Warfield | F33: PROFESSIONAL DEBT MEDIATION CAROL J. WATSON PERIOD ENDING 6/16/25 TO 7/15/25 | G33: 12 | I33: 186328.19 | J33: 09/04/2025 | K33: 2
A34: Alafaya Palms | B34: 45903 | C34: J-317122 | E34: PDM & Hunter Warfield | F34: HUNTER WARFIELD ELIZABETH CABRERA RIVERA PERIOD ENDING 7/31/25 | G34: 184.85 | I34: 186513.04 | J34: 09/04/2025 | K34: 2
A35: Alafaya Palms | B35: 45903 | C35: J-318699 | D35: Daily Deposit | E35: 09/03/2025 Daily Deposit | F35: PayLease : Cash Deposit 09/03/2025 | G35: 8167.98 | I35: 194681.02 | J35: 09/05/2025 | K35: 2
A36: Alafaya Palms | B36: 45903 | C36: J-318699 | D36: Daily Deposit | E36: 09/03/2025 Daily Deposit | F36: RP : ACH Deposit 08/29/2025 | G36: 1416 | I36: 196097.02 | J36: 09/03/2025 | K36: 2
A37: Alafaya Palms | B37: 45903 | C37: J-318699 | D37: Daily Deposit | E37: 09/03/2025 Daily Deposit | F37: RP : ACH Deposit 08/30/2025 | G37: 3696.26 | I37: 199793.28 | J37: 09/03/2025 | K37: 2
A38: Alafaya Palms | B38: 45903 | C38: J-318699 | D38: Daily Deposit | E38: 09/03/2025 Daily Deposit | F38: RP : ACH Deposit 08/31/2025 | G38: 16883.99 | I38: 216677.27 | J38: 09/03/2025 | K38: 2
A39: Alafaya Palms | B39: 45903 | C39: J-318699 | D39: Daily Deposit | E39: 09/03/2025 Daily Deposit | F39: RP : ACH Deposit 09/01/2025 | G39: 26941.26 | I39: 243618.53 | J39: 09/03/2025 | K39: 2
A40: Alafaya Palms | B40: 45903 | C40: J-318699 | D40: Daily Deposit | E40: 09/03/2025 Daily Deposit | F40: RP : ACH Deposit 09/02/2025 | G40: 19902.72 | I40: 263521.25 | J40: 09/03/2025 | K40: 2
A41: Alafaya Palms | B41: 45903 | C41: J-318699 | D41: Daily Deposit | E41: 09/03/2025 Daily Deposit | F41: RP : CC Deposit 09/03/2025 | G41: 3743.04 | I41: 267264.29 | J41: 09/08/2025 | K41: 2
A42: Alafaya Palms | B42: 45904 | C42: K-487182 | D42: 1406 | E42: DUKE ENERGY (v0000370) | F42: 07/26/2025-08/25/2025-Electric-9100 8667 2734-ELECTRIC 1-13600 WESLEYAN BLVD LITE - LIGHTING | H42: -2260.69 | I42: 265003.6 | J42: 09/05/2025 | K42: -2
A43: Alafaya Palms | B43: 45904 | C43: K-487306 | D43: 30762 | E43: Charter Communications (v0006510) | F43: ACCOUNT# 8337 10 029 1675135 CLUBHOUSE 08/18/2025-09/17/2025 INTERNET SERVICE. | H43: -115 | I43: 264888.6 | J43: 09/17/2025 | K43: -2
A44: Alafaya Palms | B44: 45904 | C44: K-487393 | D44: 1407 | E44: Lakeshore Management Inc (v0000666) | F44: PB FOR ORIGEN FINANCIAL SERVICES INV # 08-25 LAKE | H44: -323.08 | I44: 264565.52 | J44: 09/08/2025 | K44: -2
A45: Alafaya Palms | B45: 45904 | C45: K-487502 | D45: 1408 | E45: Lakeshore Management Inc (v0000666) | F45: PB YARDI INVOICE #4963826 OCTOBER 2025 | H45: -120.88 | I45: 264444.64 | J45: 09/08/2025 | K45: -2
A46: Alafaya Palms | B46: 45904 | C46: J-318805 | D46: Daily Deposit | E46: 09/04/2025 Daily Deposit | F46: CKS 09/04/2025 Batch 52543b58-6b14-4a9d-b4be-cabd47a0ce36 | G46: 966.94 | I46: 265411.58 | J46: 09/05/2025 | K46: 2
A47: Alafaya Palms | B47: 45904 | C47: J-318805 | D47: Daily Deposit | E47: 09/04/2025 Daily Deposit | F47: CKS 09/04/2025 Batch 7da7c730-16a9-4f4b-88b3-c9b7d21acce7 | G47: 970 | I47: 266381.58 | J47: 09/05/2025 | K47: 2
A48: Alafaya Palms | B48: 45904 | C48: J-318805 | D48: Daily Deposit | E48: 09/04/2025 Daily Deposit | F48: CKS 09/04/2025 Batch d6c29256-0c33-4d44-a532-e7e5ae588530 | G48: 908.08 | I48: 267289.66 | J48: 09/05/2025 | K48: 2
A49: Alafaya Palms | B49: 45904 | C49: J-318805 | D49: Daily Deposit | E49: 09/04/2025 Daily Deposit | F49: PayLease : Cash Deposit 09/04/2025 | G49: 10175.59 | I49: 277465.25 | J49: 09/08/2025 | K49: 2
A50: Alafaya Palms | B50: 45904 | C50: J-318805 | D50: Daily Deposit | E50: 09/04/2025 Daily Deposit | F50: RP : ACH Deposit 09/02/2025 | G50: 7430.31 | I50: 284895.56 | J50: 09/04/2025 | K50: 2
A51: Alafaya Palms | B51: 45904 | C51: J-318805 | D51: Daily Deposit | E51: 09/04/2025 Daily Deposit | F51: RP : ACH Deposit 09/03/2025 | G51: 33817.56 | I51: 318713.12 | J51: 09/04/2025 | K51: 2
A52: Alafaya Palms | B52: 45904 | C52: J-318805 | D52: Daily Deposit | E52: 09/04/2025 Daily Deposit | F52: RP : CC Deposit 09/04/2025 | G52: 1834.83 | I52: 320547.95 | J52: 09/08/2025 | K52: 2
A53: Alafaya Palms | B53: 45905 | C53: K-487719 | D53: 30763 | E53: LAKESIDE AQUATIC WEED CONTROL (v0000627) | F53: SEPTEMBER 2025 AQUATIC MANAGEMENT SERVICES | H53: -240 | I53: 320307.95 | J53: 09/11/2025 | K53: -2
A54: Alafaya Palms | B54: 45905 | C54: K-487720 | D54: 30764 | E54: Maintain Landscaping (v0000680) | F54: SEPTEMBER 2025 MONTHLY CONTRACTED LANDSCAPE SERVICE PHASE 3 | H54: -800 | I54: 319507.95 | J54: 09/11/2025 | K54: -2
A55: Alafaya Palms | B55: 45905 | C55: K-487721 | D55: 30765 | E55: CREATIVE MULTICARE, INC. (v0001308) | F55: LOT# 354 BACKUP - MANHOLE | H55: -425 | I55: 319082.95 | J55: 09/11/2025 | K55: -2
A56: Alafaya Palms | B56: 45905 | C56: K-487722 | D56: 30766 | E56: CREATIVE MULTICARE, INC. (v0001308) | F56: LOT# 191 6 INCH MAIN BREAK | H56: -9230.55 | I56: 309852.4 | J56: 09/11/2025 | K56: -2
A57: Alafaya Palms | B57: 45905 | C57: K-487722 | D57: 30766 | E57: CREATIVE MULTICARE, INC. (v0001308) | F57: LOT# 191 6 INCH MAIN BREAK | H57: -3 | I57: 309849.4 | J57: 09/11/2025 | K57: -2
A58: Alafaya Palms | B58: 45905 | C58: K-487723 | D58: 30767 | E58: Konica Minolta (v0001386) | F58: CN#081-0188524-000 | H58: -368.81 | I58: 309480.59 | J58: 09/11/2025 | K58: -2
A59: Alafaya Palms | B59: 45905 | C59: K-487724 | D59: 30768 | E59: MICHAEL'S LIGHTING & ELECTRIC,INC (v0003348) | F59: LOT# 173 SERVICE CALL - ELECTRICAL -08/20/2025 | H59: -90 | I59: 309390.59 | J59: 09/16/2025 | K59: -2
A60: Alafaya Palms | B60: 45905 | C60: K-487725 | D60: 30769 | E60: United Site Services (v0004129) | F60: RENTAL CHARGE 08/26/2025-09/22/2025 1 SERVICE 2 DAYS PER WEEK | H60: -471.7 | I60: 308918.89 | J60: 09/15/2025 | K60: -2
A61: Alafaya Palms | B61: 45905 | C61: K-487726 | D61: 30770 | E61: Twisted Artz LLC d/b/a Party People Events (v0009797) | F61: Helium Tank Rental | H61: -26.09 | I61: 308892.8 | J61: 09/15/2025 | K61: -2
A62: Alafaya Palms | B62: 45905 | C62: J-318862 | D62: Daily Deposit | E62: 09/05/2025 Daily Deposit | F62: EFT Deposit 09/05/2025 | G62: 11062.42 | I62: 319955.22 | J62: 09/08/2025 | K62: 2
A63: Alafaya Palms | B63: 45905 | C63: J-318862 | D63: Daily Deposit | E63: 09/05/2025 Daily Deposit | F63: NSF RP : ACH Deposit 08/29/2025 | H63: -1416 | I63: 318539.22 | J63: 09/05/2025 | K63: -2
A64: Alafaya Palms | B64: 45905 | C64: J-318862 | D64: Daily Deposit | E64: 09/05/2025 Daily Deposit | F64: PayLease : Cash Deposit 09/05/2025 | G64: 17657.71 | I64: 336196.93 | J64: 09/09/2025 | K64: 2
A65: Alafaya Palms | B65: 45905 | C65: J-318862 | D65: Daily Deposit | E65: 09/05/2025 Daily Deposit | F65: RP : ACH Deposit 09/03/2025 | G65: 7501.89 | I65: 343698.82 | J65: 09/05/2025 | K65: 2
A66: Alafaya Palms | B66: 45905 | C66: J-318862 | D66: Daily Deposit | E66: 09/05/2025 Daily Deposit | F66: RP : ACH Deposit 09/04/2025 | G66: 31666.27 | I66: 375365.09 | J66: 09/05/2025 | K66: 2
A67: Alafaya Palms | B67: 45905 | C67: J-318862 | D67: Daily Deposit | E67: 09/05/2025 Daily Deposit | F67: RP : CC Deposit 09/05/2025 | G67: 2909.41 | I67: 378274.5 | J67: 09/08/2025 | K67: 2
A68: Alafaya Palms | B68: 45906 | C68: J-319014 | D68: Daily Deposit | E68: 09/06/2025 Daily Deposit | F68: PayLease : Cash Deposit 09/06/2025 | G68: 913.89 | I68: 379188.39 | J68: 09/09/2025 | K68: 2
A69: Alafaya Palms | B69: 45908 | C69: K-488004 | D69: 1409 | E69: Lakeshore Management Inc (v0000666) | F69: MA PAYBACK SEPTEMBER 2025 | H69: -610.14 | I69: 378578.25 | J69: 09/10/2025 | K69: -2
A70: Alafaya Palms | B70: 45908 | C70: K-488132 | D70: 1410 | E70: Lakeshore Management Inc (v0000666) | F70: PB FOR PAINT THE WEB INV # 1360 | H70: -223.27 | I70: 378354.98 | J70: 09/10/2025 | K70: -2
A71: Alafaya Palms | B71: 45908 | C71: K-488413 | D71: 1411 | E71: LSC Mobile Sales - Tranche A (v0007540) | F71: AUG 2025 PARK TO HOME TRANSFER | H71: -21748.98 | I71: 356606 | J71: 09/09/2025 | K71: -2
A72: Alafaya Palms | B72: 45908 | C72: J-319471 | D72: Daily Deposit | E72: 09/08/2025 Daily Deposit | F72: CKS 09/08/2025 Batch 4d1fab87-99f4-43a7-9fe3-ba87c17faad7 | G72: 954.58 | I72: 357560.58 | J72: 09/09/2025 | K72: 2
A73: Alafaya Palms | B73: 45908 | C73: J-319471 | D73: Daily Deposit | E73: 09/08/2025 Daily Deposit | F73: CKS 09/08/2025 Batch 869b0ee3-a125-4aec-8d5a-fba3eef993dd | G73: 7325.97 | I73: 364886.55 | J73: 09/09/2025 | K73: 2
A74: Alafaya Palms | B74: 45908 | C74: J-319471 | D74: Daily Deposit | E74: 09/08/2025 Daily Deposit | F74: CKS 09/08/2025 Batch 8b18b2a7-a1c7-451a-8c22-0526a2b9f431 | G74: 1107 | I74: 365993.55 | J74: 09/09/2025 | K74: 2
A75: Alafaya Palms | B75: 45908 | C75: J-319471 | D75: Daily Deposit | E75: 09/08/2025 Daily Deposit | F75: CKS 09/08/2025 Batch b8ac3f36-fae2-4009-9f44-b8dda740585a | G75: 2742.27 | I75: 368735.82 | J75: 09/09/2025 | K75: 2
A76: Alafaya Palms | B76: 45908 | C76: J-319471 | D76: Daily Deposit | E76: 09/08/2025 Daily Deposit | F76: CKS 09/08/2025 Batch c4496786-51d1-49a3-b7fd-07c3834e2243 | G76: 1756.58 | I76: 370492.4 | J76: 09/09/2025 | K76: 2
A77: Alafaya Palms | B77: 45908 | C77: J-319471 | D77: Daily Deposit | E77: 09/08/2025 Daily Deposit | F77: CKS 09/08/2025 Batch eae4d16f-d455-4e68-96af-3cde254d2e04 | G77: 1732.58 | I77: 372224.98 | J77: 09/09/2025 | K77: 2
A78: Alafaya Palms | B78: 45908 | C78: J-319471 | D78: Daily Deposit | E78: 09/08/2025 Daily Deposit | F78: RP : ACH Deposit 09/04/2025 | G78: 2743.81 | I78: 374968.79 | J78: 09/08/2025 | K78: 2
A79: Alafaya Palms | B79: 45908 | C79: J-319471 | D79: Daily Deposit | E79: 09/08/2025 Daily Deposit | F79: RP : ACH Deposit 09/05/2025 | G79: 99936.85 | I79: 474905.64 | J79: 09/08/2025 | K79: 2
A80: Alafaya Palms | B80: 45908 | C80: J-319471 | D80: Daily Deposit | E80: 09/08/2025 Daily Deposit | F80: RP : CC Deposit 09/08/2025 | G80: 919.19 | I80: 475824.83 | J80: 09/09/2025 | K80: 2
A81: Alafaya Palms | B81: 45909 | C81: K-488475 | D81: 30771 | E81: DISPOSALL, INC. (v0001311) | F81: 08/01/2025-08/31/2025-Trash-01-453863 0-TRASH 2-13600 WESLEYAN BLVD | H81: -244.95 | I81: 475579.88 | J81: 09/16/2025 | K81: -2
A82: Alafaya Palms | B82: 45909 | C82: K-488490 | D82: 1412 | E82: DUKE ENERGY (v0000370) | F82: 08/05/2025-09/03/2025-Electric-9101 8666 0421-4046461-1826 Rockhurst Ave | H82: -101.91 | I82: 475477.97 | J82: 09/10/2025 | K82: -2
A83: Alafaya Palms | B83: 45909 | C83: K-488491 | D83: 1413 | E83: DUKE ENERGY (v0000370) | F83: 08/05/2025-09/03/2025-Electric-9101 8666 1274-3425612-13615 BRIGHAM YOUNG DRIVE | H83: -128 | I83: 475349.97 | J83: 09/10/2025 | K83: -2
A84: Alafaya Palms | B84: 45909 | C84: K-488492 | D84: 1414 | E84: DUKE ENERGY (v0000370) | F84: Electric-9101 4168 3197-198-08/05/2025-09/03/2025 - 30 Days Vacant | H84: -33.71 | I84: 475316.26 | J84: 09/10/2025 | K84: -2
A85: Alafaya Palms | B85: 45909 | C85: K-488493 | D85: 1415 | E85: DUKE ENERGY (v0000370) | F85: Electric-9101 4613 3077-463-08/05/2025-09/03/2025 - 30 Days Vacant | H85: -155.52 | I85: 475160.74 | J85: 09/10/2025 | K85: -2
A86: Alafaya Palms | B86: 45909 | C86: K-488494 | D86: 1416 | E86: DUKE ENERGY (v0000370) | F86: Electric-9101 5443 8987-56-08/19/2025-09/03/2025 - 16 Days Vacant | H86: -66.04 | I86: 475094.7 | J86: 09/10/2025 | K86: -2
A87: Alafaya Palms | B87: 45909 | C87: K-488562 | D87: 1417 | E87: Lakeshore Management Inc (v0000666) | F87: PB for LeadCrossing INV-000611 | H87: -1623.58 | I87: 473471.12 | J87: 09/11/2025 | K87: -2
A88: Alafaya Palms | B88: 45909 | C88: K-488587 | D88: 1418 | E88: Lakeshore Management Inc (v0000666) | F88: PB for LeadCrossing INV-000612 | H88: -275.06 | I88: 473196.06 | J88: 09/11/2025 | K88: -2
A89: Alafaya Palms | B89: 45909 | C89: K-488615 | D89: 1419 | E89: Lakeshore Management Inc (v0000666) | F89: PB FOR SPECTRUM ACCOUNT# 8337 10 699 0032874 08/17/25-09/16/25 | H89: -160 | I89: 473036.06 | J89: 09/11/2025 | K89: -2
A90: Alafaya Palms | B90: 45909 | C90: J-319548 | D90: Daily Deposit | E90: 09/09/2025 Daily Deposit | F90: CKS 09/09/2025 Batch 3d380b59-8ec5-43c3-b68c-1bdcbd7331f7 | G90: 1967.44 | I90: 475003.5 | J90: 09/10/2025 | K90: 2
A91: Alafaya Palms | B91: 45909 | C91: J-319548 | D91: Daily Deposit | E91: 09/09/2025 Daily Deposit | F91: NSF RP : ACH Deposit 09/03/2025 | H91: -924.15 | I91: 474079.35 | J91: 09/09/2025 | K91: -2
A92: Alafaya Palms | B92: 45909 | C92: J-319548 | D92: Daily Deposit | E92: 09/09/2025 Daily Deposit | F92: RP : ACH Deposit 09/05/2025 | G92: 14743.28 | I92: 488822.63 | J92: 09/09/2025 | K92: 2
A93: Alafaya Palms | B93: 45909 | C93: J-319548 | D93: Daily Deposit | E93: 09/09/2025 Daily Deposit | F93: RP : ACH Deposit 09/06/2025 | G93: 6438.63 | I93: 495261.26 | J93: 09/09/2025 | K93: 2
A94: Alafaya Palms | B94: 45909 | C94: J-319548 | D94: Daily Deposit | E94: 09/09/2025 Daily Deposit | F94: RP : ACH Deposit 09/07/2025 | G94: 1154.18 | I94: 496415.44 | J94: 09/09/2025 | K94: 2
A95: Alafaya Palms | B95: 45910 | C95: K-488728 | D95: 1420 | E95: Lakeshore Management Inc (v0000666) | F95: T-Mobile Invoices Through 8.30.25 | H95: -117.67 | I95: 496297.77 | J95: 09/15/2025 | K95: -2
A96: Alafaya Palms | B96: 45910 | C96: K-488859 | D96: 1421 | E96: DUKE ENERGY (v0000370) | F96: Electric-9101 4847 9226-114-08/05/2025-09/03/2025 - 30 Days Vacant | H96: -100.14 | I96: 496197.63 | J96: 09/12/2025 | K96: -2
A97: Alafaya Palms | B97: 45910 | C97: K-489006 | D97: 1422 | E97: Lakeshore Management Inc (v0000666) | F97: PB YARDI INVOICE #4975928 AUGUST 2025 | H97: -5 | I97: 496192.63 | J97: 09/12/2025 | K97: -2
A98: Alafaya Palms | B98: 45910 | C98: K-489158 | D98: 1423 | E98: Lakeshore Management Inc (v0000666) | F98: PB FOR RESULT TECH INV # 2454 | H98: -27.7 | I98: 496164.93 | J98: 09/15/2025 | K98: -2
A99: Alafaya Palms | B99: 45910 | C99: K-489288 | D99: 1424 | E99: Lakeshore Management Inc (v0000666) | F99: PB FOR SEPTEMBER 25?ADT | H99: -185.71 | I99: 495979.22 | J99: 09/15/2025 | K99: -2
A100: Alafaya Palms | B100: 45910 | C100: K-489288 | D100: 1424 | E100: Lakeshore Management Inc (v0000666) | F100: PB FOR SEPTEMBER 25?ADT | H100: -50.85 | I100: 495928.37 | J100: 09/15/2025 | K100: -2
...

Sheet Un-Reconcile transactions
A1: Bank
A2: Property Name | B2: Date | C2: Control | D2: Reference | E2: Description | F2: Remarks | G2: Amount | H2: Comment
A3: Alafaya Palms | B3: 09/30/2025 | F3: STAGECOACH SWEEP DEBIT | G3: -455713.94 | H3: AP | I3: Will be reversed on 10/01/2025
G4: =SUM(G3:G3) -> -455713.94
A6: GL
A7: Property Name | B7: Date | C7: Control | D7: Reference | E7: Description | F7: Remarks | G7: Amount | H7: Comment
A8: Alafaya Palms | B8: 45929 | C8: J-320131 | D8: Deposit of 09-2025 transfer funds for SD activity | E8: Deposit of 09-2025 transfer funds for SD activity | F8: Deposit of 09-2025 transfer funds for SD activity | G8: 2187.78 | H8: AR | I8: Will clear on 10/03/2025 with bank transaction
A9: Alafaya Palms | B9: 45929 | C9: J-320135 | D9: Daily Deposit | E9: 09/29/2025 Daily Deposit | F9: PayLease : Cash Deposit 09/29/2025 | G9: 899.73 | H9: AR | I9: Will clear on 10/01/2025 with bank transaction
A10: Alafaya Palms | B10: 45930 | C10: J-320325 | D10: Daily Deposit | E10: 09/30/2025 Daily Deposit | F10: CKS 09/30/2025 Batch 0795459c-c2d8-4c95-84e6-5ba56062a645 | G10: 1735.36 | H10: AR | I10: Will clear on 10/01/2025 with bank transaction
A11: Alafaya Palms | B11: 45930 | C11: J-320325 | D11: Daily Deposit | E11: 09/30/2025 Daily Deposit | F11: CKS 09/30/2025 Batch 58ceb15e-b2cf-463e-8b75-06a3184abba6 | G11: 3495 | H11: AR | I11: Will clear on 10/01/2025 with bank transaction
A12: Alafaya Palms | B12: 45930 | C12: J-320325 | D12: Daily Deposit | E12: 09/30/2025 Daily Deposit | F12: CKS 09/30/2025 Batch 63686773-08b8-442d-ae6d-a114e92eccb1 | G12: 977 | H12: AR | I12: Will clear on 10/01/2025 with bank transaction
A13: Alafaya Palms | B13: 45930 | C13: J-320325 | D13: Daily Deposit | E13: 09/30/2025 Daily Deposit | F13: PayLease : Cash Deposit 09/30/2025 | G13: 914.98 | H13: AR | I13: Will clear on 10/02/2025 with bank transaction
A14: Alafaya Palms | B14: 45930 | C14: J-320325 | D14: Daily Deposit | E14: 09/30/2025 Daily Deposit | F14: RP : CC Deposit 09/30/2025 | G14: 918.72 | H14: AR | I14: Will clear on 10/01/2025 with bank transaction
A15: Alafaya Palms | B15: 45930 | C15: J-325125 | D15: 9.2025 PB Free Lot rent | E15: 9.2025 PB Free Lot rent | F15: 9.25 PB Free Lot rent-Alafaya Palms OMAR QUINONEZ #173 | G15: 270 | H15: AR | I15: Will clear on 10/03/2025 with bank transaction
G16: =SUM(G8:G15) -> 11398.57
A18: Alafaya Palms | B18: 45923 | C18: K-492078 | D18: 30779 | E18: Yes Energy Management, Inc. (v0002908) | F18: Utility Invoice Processing (UEM) 08/01/2025 - 08/31/2025 Inv# 1283008 | G18: -63 | H18: AP | I18: Will clear on 10/02/2025 with bank transaction
A19: Alafaya Palms | B19: 45926 | C19: K-493064 | D19: 30780 | E19: Atlas Law (v0000101) | F19: LOT# 365 RODRIGUEZ FERNANDEZ | G19: -1473.99 | H19: AP | I19: Will clear on 10/06/2025 with bank transaction
A20: Alafaya Palms | B20: 45926 | C20: K-493064 | D20: 30780 | E20: Atlas Law (v0000101) | F20: LOT# 205 DIAZ MORENO | G20: -1325.02 | H20: AP
A21: Alafaya Palms | B21: 45926 | C21: K-493064 | D21: 30780 | E21: Atlas Law (v0000101) | F21: LOT# 305 ARTZBERGER | G21: -532.84 | H21: AP
A22: Alafaya Palms | B22: 45926 | C22: K-493064 | D22: 30780 | E22: Atlas Law (v0000101) | F22: LOT# 345 OQUENDO | G22: -75.74 | H22: AP
A23: Alafaya Palms | B23: 45926 | C23: K-493064 | D23: 30780 | E23: Atlas Law (v0000101) | F23: LOT# 22 TOMKO | G23: -150 | H23: AP
A24: Alafaya Palms | B24: 45926 | C24: K-493064 | D24: 30780 | E24: Atlas Law (v0000101) | F24: LOT# 262 DELIZ | G24: -45 | H24: AP
A25: Alafaya Palms | B25: 45926 | C25: K-493064 | D25: 30780 | E25: Atlas Law (v0000101) | F25: LOT# 206 GREEN | G25: -5.36 | H25: AP
A26: Alafaya Palms | B26: 45926 | C26: K-493064 | D26: 30780 | E26: Atlas Law (v0000101) | F26: LOT# 206 GREEN | G26: -13.04 | H26: AP
A27: Alafaya Palms | B27: 45926 | C27: K-493064 | D27: 30780 | E27: Atlas Law (v0000101) | F27: LOT# 71 MONICK | G27: -100 | H27: AP
A28: Alafaya Palms | B28: 45926 | C28: K-493064 | D28: 30780 | E28: Atlas Law (v0000101) | F28: LOT# 56 ROMAN | G28: -949.59 | H28: AP
A29: Alafaya Palms | B29: 45926 | C29: K-493064 | D29: 30780 | E29: Atlas Law (v0000101) | F29: LOT# 396 VINCENTY | G29: -1231.53 | H29: AP
A30: Alafaya Palms | B30: 45926 | C30: K-493064 | D30: 30780 | E30: Atlas Law (v0000101) | F30: LOT# 218 STAUFFER | G30: -981.37 | H30: AP
A31: Alafaya Palms | B31: 45926 | C31: K-493064 | D31: 30780 | E31: Atlas Law (v0000101) | F31: LOT# 246 LAUREANO | G31: -150 | H31: AP
A32: Alafaya Palms | B32: 45926 | C32: K-493064 | D32: 30780 | E32: Atlas Law (v0000101) | F32: LOT# 82 SANCHEZ-COSME | G32: -1325.02 | H32: AP
A33: Alafaya Palms | B33: 45929 | C33: K-493359 | D33: 30781 | E33: Charter Communications (v0006510) | F33: ACCOUNT# 8337 10 029 1675135 CLUBHOUSE 09/18/2025-10/17/2025 INTERNET SERVICE. | G33: -123.95 | H33: AP | I33: Will clear on 10/09/2025 with bank transaction
A34: Alafaya Palms | B34: 45930 | C34: K-493554 | D34: 30783 | E34: Hunter Warfield (v0007270) | F34: Court Fee Lot 50 Vazquez | G34: -5.95 | H34: AP | I34: Showing outstanding status in bank
A35: Alafaya Palms | B35: 45930 | C35: K-493554 | D35: 30783 | E35: Hunter Warfield (v0007270) | F35: Court Fee Lot 50 Vazquez | G35: -10 | H35: AP
A36: Alafaya Palms | B36: 45930 | C36: K-493554 | D36: 30783 | E36: Hunter Warfield (v0007270) | F36: Court Fee Lot 50 Vazquez | G36: -3 | H36: AP
A37: Alafaya Palms | B37: 45930 | C37: K-493554 | D37: 30783 | E37: Hunter Warfield (v0007270) | F37: Court Fee Lot 500 Cabrera | G37: -184.85 | H37: AP
A38: Alafaya Palms | B38: 45930 | C38: K-493554 | D38: 30783 | E38: Hunter Warfield (v0007270) | F38: Court Fee Lot 220 Gonzalez | G38: -74.95 | H38: AP
A39: Alafaya Palms | B39: 45930 | C39: K-493554 | D39: 30783 | E39: Hunter Warfield (v0007270) | F39: Court Fee Lot 220 Gonzalez | G39: -167 | H39: AP
A40: Alafaya Palms | B40: 45930 | C40: K-493627 | D40: 1446 | E40: Pennoni (v0007120) | F40: TZ-orange county permits | G40: -1027.5 | H40: AP | I40: Will clear on 10/02/2025 with bank transaction
A41: Alafaya Palms | B41: 45930 | C41: K-493746 | D41: 1447 | E41: Lakeshore Management Inc (v0000666) | F41: Batch#78964 Enterprise | G41: -29.82 | H41: AP | I41: Will clear on 10/01/2025 with bank transaction
A42: Alafaya Palms | B42: 45930 | C42: J-320322 | D42: 9/2025 Mortgages 2-40 | E42: 9/2025 Mortgages 2-40 | F42: Lakeshore University LLC mtg pymt | G42: -193875.17 | H42: AP | I42: Will clear on 10/06/2025 with bank transaction
A43: Alafaya Palms | B43: 45930 | C43: J-323192 | D43: Park Mgmt Fees Sept 2025 | E43: Park Mgmt Fees Sept 2025 :Reversed by J-323339 | F43: Park Mgmt Fees Sept 2025 :Reversed by J-323339 | G43: -22690.01 | H43: AP | I43: Will be reversed on 10/01/2025 with J-323339
A44: Alafaya Palms | B44: 45930 | C44: J-325227 | E44: MA September Cash Park to Home :Reversed by J-325304 | F44: MA September Cash Park to Home | G44: -17770.6 | H44: AP | I44: Will be reversed on 10/01/2025 with J-325304
G45: =SUM(G18:G44) -> -244384.3

Sheet Old Reconciled
A1: Bank
A2: Property name | B2: Date | C2: Amount | D2: Check Number | E2: Description | F2: Remarks | G2: Code
A3: Alafaya Palms | B3: 08/29/2025 | C3: -387642.13 | F3: STAGECOACH SWEEP DEBIT | G3: -4
A5: GL
A6: Property name | B6: Date | C6: Control | D6: Reference | E6: Description | F6: Remarks | G6: Debit | J6: Reconcile Date | K6: Code
A7: Alafaya Palms | B7: 45898 | C7: J-313621 | D7: Daily Deposit | E7: 08/29/2025 Daily Deposit | F7: PayLease : Cash Deposit 08/29/2025 | G7: 6696.14 | J7: 09/03/2025 | K7: 3
A8: Alafaya Palms | B8: 45898 | C8: J-313621 | D8: Daily Deposit | E8: 08/29/2025 Daily Deposit | F8: RP : CC Deposit 08/29/2025 | G8: 2061.1 | J8: 09/02/2025 | K8: 3
A9: Alafaya Palms | B9: 45899 | C9: J-316898 | D9: 8.2025 PB Free Lot rent | E9: 8.2025 PB Free Lot rent | F9: 8.25 PB Free Lot rent-Alafaya Palms OMAR QUINONEZ #173 | G9: 270 | J9: 09/04/2025 | K9: 3
A10: Alafaya Palms | B10: 45900 | C10: J-313626 | D10: Daily Deposit | E10: 08/31/2025 Daily Deposit | F10: PayLease : Cash Deposit 08/31/2025 | G10: 950.06 | J10: 09/03/2025 | K10: 3
A11: Alafaya Palms | B11: 45894 | C11: K-484450 | D11: 30754 | E11: Staples Bus (v0001011) | F11: ORDER# 7663140333-000-001 BY MARILYN GONZALEZ | H11: -137.76 | J11: 09/02/2025 | K11: -3
A12: Alafaya Palms | B12: 45894 | C12: K-484498 | D12: 30755 | E12: Atlas Law (v0000101) | F12: LOT# 71 MONICK | H12: -634.09 | J12: 09/04/2025 | K12: -3
A13: Alafaya Palms | B13: 45894 | C13: K-484498 | D13: 30755 | E13: Atlas Law (v0000101) | F13: LOT# 305 ARTZBERGER | H13: -787.87 | J13: 09/04/2025 | K13: -3
A14: Alafaya Palms | B14: 45894 | C14: K-484498 | D14: 30755 | E14: Atlas Law (v0000101) | F14: LOT# 345 OQUENDO | H14: -451.77 | J14: 09/04/2025 | K14: -3
A15: Alafaya Palms | B15: 45894 | C15: K-484498 | D15: 30755 | E15: Atlas Law (v0000101) | F15: AP vs Calo | H15: -405.99 | J15: 09/04/2025 | K15: -3
A16: Alafaya Palms | B16: 45894 | C16: K-484498 | D16: 30755 | E16: Atlas Law (v0000101) | F16: AP vs Tomko | H16: -300 | J16: 09/04/2025 | K16: -3
A17: Alafaya Palms | B17: 45894 | C17: K-484498 | D17: 30755 | E17: Atlas Law (v0000101) | F17: AP vs Green | H17: -875 | J17: 09/04/2025 | K17: -3
A18: Alafaya Palms | B18: 45894 | C18: K-484499 | D18: 30756 | E18: CENTRAL WATER & ELECTRIC UTILITY SERVICES (v0000190) | F18: BOIL ADVISORY BACTERIOLOGICAL SAMPLES | H18: -550 | J18: 09/05/2025 | K18: -3
A19: Alafaya Palms | B19: 45894 | C19: K-484500 | D19: 30757 | E19: Lutz Bobo & Telfair PA (v0001333) | F19: Prospectus amendments | H19: -255 | J19: 09/04/2025 | K19: -3
A20: Alafaya Palms | B20: 45895 | C20: K-484970 | D20: 30758 | E20: Atlas Law (v0000101) | F20: AP vs Vasquez | H20: -1307.15 | J20: 09/04/2025 | K20: -3
A21: Alafaya Palms | B21: 45895 | C21: K-485115 | D21: 30759 | E21: Yes Energy Management, Inc. (v0002908) | F21: Utility Invoice Processing (UEM) 07/01/2025 - 07/31/2025 Inv# 1265790 | H21: -56 | J21: 09/12/2025 | K21: -3
A22: Alafaya Palms | B22: 45898 | C22: K-485856 | D22: 1403 | E22: DUKE ENERGY (v0000370) | F22: 07/29/2025-08/26/2025-Electric-9101 4870 5160-Electric Outdoor-0 Wesleyan blvd | H22: -165.52 | J22: 09/02/2025 | K22: -3
... A24: Alafaya Palms | B24: 45900 | C24: J-313554 | D24: 8/2025 Mortgages 2-40 | E24: 8/2025 Mortgage Payments 2-40 | F24: Lakeshore University LLC mtg pymt | H24: -198634.81 | J24: 09/05/2025 | K24: -3
A25: Alafaya Palms | B25: 45900 | C25: J-315814 | D25: Park Mgmt Fees Aug 2025 | E25: Park Mgmt Fees Aug 2025 :Reversed by J-315961 | F25: Park Mgmt Fees Aug 2025 :Reversed by J-315961 | H25: -22750.99 | J25: 45901 | K25: -4
A26: Alafaya Palms | B26: 45900 | C26: J-319040 | E26: MA August Cash Park to Home :Reversed by J-319115 | F26: MA August Cash Park to Home | H26: -21748.98 | J26: 45901 | K26: -4
